pyCoW
