Metadata-Version: 1.1
Name: pyCoW
Version: 0.0.4
Summary: Copy-On-Write Mixin Base Class.
Home-page: https://github.com/bannsec/pyCoW
Author: Michael Bann
Author-email: self@bannsecurity.com
License: MIT
Keywords: copy-on-write cow
Platform: UNKNOWN
Classifier: License :: OSI Approved :: MIT License
Classifier: Programming Language :: Python :: 3
